cp2kdata/__init__.py
cp2kdata/cell.py
cp2kdata/dpdata_plugin.py
cp2kdata/log.py
cp2kdata/output.py
cp2kdata/test_input.py
cp2kdata/units.py
cp2kdata/utils.py
cp2kdata/block_parser/__init__.py
cp2kdata/block_parser/atomic_kind.py
cp2kdata/block_parser/cells.py
cp2kdata/block_parser/converge.py
cp2kdata/block_parser/coordinates.py
cp2kdata/block_parser/dft_plus_u.py
cp2kdata/block_parser/dipole.py
cp2kdata/block_parser/energies.py
cp2kdata/block_parser/errors_handle.py
cp2kdata/block_parser/fep.py
cp2kdata/block_parser/forces.py
cp2kdata/block_parser/geo_opt.py
cp2kdata/block_parser/header_info.py
cp2kdata/block_parser/hirshfeld.py
cp2kdata/block_parser/md_xyz.py
cp2kdata/block_parser/mulliken.py
cp2kdata/block_parser/stress.py
cp2kdata/block_parser/vibration.py
cp2kdata/cli/__init__.py
cp2kdata/cli/cmd.py
cp2kdata/cli/funcs.py
cp2kdata/cube/__init__.py
cp2kdata/cube/cube.py
cp2kdata/matplotlibstyle/__init__.py
cp2kdata/matplotlibstyle/jacs.mplstyle
cp2kdata/matplotlibstyle/jcp.mplstyle
cp2kdata/pdos/__init__.py
cp2kdata/pdos/pdos.py
cp2kdata/plots/__init__.py
cp2kdata/plots/colormaps.py
cp2kdata/plots/fep_plot.py
cp2kdata/plots/geo_opt_plot.py
cp2kdata/plots/test_plot.py
cp2kdata-0.7.3.dist-info/licenses/LICENSE
cp2kdata-0.7.3.dist-info/METADATA
cp2kdata-0.7.3.dist-info/WHEEL
cp2kdata-0.7.3.dist-info/entry_points.txt
cp2kdata-0.7.3.dist-info/top_level.txt
cp2kdata-0.7.3.dist-info/RECORD
