Metadata-Version: 2.4
Name: Cp2kData
Version: 0.7.3
Summary: A Small Package to Postprocess Cp2k Output
Author-email: Yong-Bin Zhuang <robinzhuang@outlook.com>
Maintainer-email: Yong-Bin Zhuang <robinzhuang@outlook.com>
License:                    GNU LESSER GENERAL PUBLIC LICENSE
Project-URL: homepage, https://github.com/robinzyb/cp2kdata
Project-URL: repository, https://github.com/robinzyb/cp2kdata
Keywords: cp2k,cp2kdata
Classifier: Programming Language :: Python :: 3.8
Classifier: Programming Language :: Python :: 3.9
Classifier: Programming Language :: Python :: 3.10
Classifier: License :: OSI Approved :: GNU Library or Lesser General Public License (LGPL)
Requires-Python: >=3.8
License-File: LICENSE
Requires-Dist: numpy>=1.21.6
Requires-Dist: scipy>=1.5.4
Requires-Dist: matplotlib>=3.3.2
Requires-Dist: ase>=3.20.1
Requires-Dist: cp2k-input-tools
Requires-Dist: dpdata
Requires-Dist: click
Requires-Dist: regex
Requires-Dist: monty
Requires-Dist: pyyaml
Requires-Dist: pycp2k
Requires-Dist: asciichartpy
Dynamic: license-file
